{
	"type": "FeatureCollection",
	"features": [
		{
			"type": "Feature",
			"id": "demo-park-riverside",
			"geometry": {
				"type": "Point",
				"coordinates": [10.5182, 52.2684]
			},
			"properties": {
				"id": "demo-park-riverside",
				"name": "Riverside Park",
				"listInformation": "Green space along the river",
				"description": "<p>Quiet park with walking paths and picnic areas.</p>"
			}
		},
		{
			"type": "Feature",
			"id": "demo-park-central",
			"geometry": {
				"type": "Point",
				"coordinates": [10.5251, 52.2648]
			},
			"properties": {
				"id": "demo-park-central",
				"name": "Central Gardens",
				"listInformation": "Formal gardens in the city center",
				"description": "<p>Shaded benches and seasonal flower beds.</p>"
			}
		},
		{
			"type": "Feature",
			"id": "demo-park-hilltop",
			"geometry": {
				"type": "Point",
				"coordinates": [10.5316, 52.2612]
			},
			"properties": {
				"id": "demo-park-hilltop",
				"name": "Hilltop Lookout",
				"listInformation": "Small park with a viewpoint",
				"description": "<p>Panoramic views over the old town.</p>"
			}
		}
	]
}
